erech/__init__.py
erech/chains.py
erech/plugin.py
erech/py.typed
erech-0.0.10.dist-info/METADATA
erech-0.0.10.dist-info/WHEEL
erech-0.0.10.dist-info/entry_points.txt
erech-0.0.10.dist-info/RECORD
